Metadata-Version: 2.1
Name: WLed-Control
Version: 1.3.2
Summary: A very basic WLed control library
Home-page: UNKNOWN
Author: Kasper H. Larsen
Author-email: kasperhornlarsen@gmail.com
License: MIT
Keywords: Wled
Platform: UNKNOWN
Classifier: Development Status :: 5 - Production/Stable
Classifier: Intended Audience :: Education
Classifier: Operating System :: Microsoft :: Windows :: Windows 10
Classifier: License :: OSI Approved :: MIT License
Classifier: Programming Language :: Python :: 3
License-File: LICENCE.txt
